multibrain/__init__.py
multibrain/_version.py
multibrain/py.typed
multibrain/api/__init__.py
multibrain/api/launch.py
multibrain/api/main.py
multibrain/api/routes/__init__.py
multibrain/api/routes/router.py
multibrain/api/routes/streaming.py
multibrain-0.5.2.dist-info/licenses/LICENSE-CC.txt
multibrain-0.5.2.dist-info/licenses/LICENSE-apache.txt
multibrain-0.5.2.dist-info/METADATA
multibrain-0.5.2.dist-info/WHEEL
multibrain-0.5.2.dist-info/entry_points.txt
multibrain-0.5.2.dist-info/top_level.txt
multibrain-0.5.2.dist-info/RECORD
