Metadata-Version: 2.4
Name: multibrain
Version: 0.5.2
Summary: Run queries with multiple AI servers
Author-email: Jeff Moe <moe@spacecruft.org>
License: Apache 2.0
Project-URL: Homepage, https://spacecruft.org/deepcrayon/multibrain
Project-URL: Documentation, https://spacecruft.org/deepcrayon/multibrain
Project-URL: Repository, https://spacecruft.org/deepcrayon/multibrain
Project-URL: Issues, https://spacecruft.org/deepcrayon/multibrain
Project-URL: Changelog, https://spacecruft.org/deepcrayon/multibrain/raw/branch/main/CHANGELOG.txt
Keywords: ai,fastapi,inference,openai,llm
Classifier: Development Status :: 3 - Alpha
Classifier: Environment :: Console
Classifier: Intended Audience :: Developers
Classifier: License :: OSI Approved :: Apache Software License
Classifier: Natural Language :: English
Classifier: Operating System :: OS Independent
Classifier: Programming Language :: Python :: 3
Classifier: Topic :: Scientific/Engineering :: Artificial Intelligence
Requires-Python: >=3.9
License-File: LICENSE-CC.txt
License-File: LICENSE-apache.txt
Requires-Dist: fastapi
Requires-Dist: httpx
Requires-Dist: markdown2[all]
Requires-Dist: python-multipart
Requires-Dist: uvicorn
Requires-Dist: sse-starlette
Requires-Dist: pydantic>=2.0
Provides-Extra: dev
Requires-Dist: black; extra == "dev"
Requires-Dist: build; extra == "dev"
Requires-Dist: ruff; extra == "dev"
Requires-Dist: setuptools-scm; extra == "dev"
Requires-Dist: twine; extra == "dev"
Dynamic: license-file
